{
  "locale": "ru",
  "country": {
    "id": 57,
    "code": "CY",
    "iso3": "CYP",
    "numeric_code": "196",
    "name": "Кипр",
    "name_default": "Cyprus",
    "native": "Κύπρος",
    "capital": "Nicosia",
    "phonecode": "357",
    "currency": "EUR",
    "currency_name": "Euro",
    "currency_symbol": "€",
    "tld": ".cy",
    "population": 966400,
    "gdp": 38736,
    "region": "Europe",
    "region_id": 4,
    "subregion": "Southern Europe",
    "subregion_id": 16,
    "nationality": "Cypriot",
    "timezones": [
      {
        "zoneName": "Asia/Famagusta",
        "gmtOffset": 7200,
        "gmtOffsetName": "UTC+02:00",
        "abbreviation": "EET",
        "tzName": "Eastern European Time"
      },
      {
        "zoneName": "Asia/Nicosia",
        "gmtOffset": 7200,
        "gmtOffsetName": "UTC+02:00",
        "abbreviation": "EET",
        "tzName": "Eastern European Time"
      }
    ],
    "latitude": "35.00000000",
    "longitude": "33.00000000",
    "emoji": "🇨🇾",
    "emojiU": "U+1F1E8 U+1F1FE"
  },
  "state": {
    "id": 749,
    "code": "04",
    "iso2": "04",
    "iso3166_2": "CY-04",
    "fips_code": "01",
    "name": "Famagusta (Mağusa)",
    "name_default": "Famagusta (Mağusa)",
    "native": "Αμμάγκουστ (Αμμάγκουστε)",
    "type": "district",
    "level": null,
    "parent_id": null,
    "population": null,
    "latitude": "35.13521370",
    "longitude": "33.92398310",
    "timezone": "Asia/Famagusta",
    "wikiDataId": "Q59148",
    "country_code": "CY"
  },
  "cities": [
    {
      "id": 22011,
      "name": "Ачериту",
      "name_default": "Acherítou",
      "native": "Αχερίτου",
      "type": "city",
      "level": null,
      "parent_id": null,
      "population": 1556,
      "latitude": "35.10022000",
      "longitude": "33.86155000",
      "timezone": "Asia/Famagusta",
      "wikiDataId": "Q489776",
      "country_code": "CY",
      "state_code": "04",
      "state_id": 749,
      "country_id": 57
    },
    {
      "id": 22102,
      "name": "Ачна",
      "name_default": "Áchna",
      "native": "Άχνα",
      "type": "city",
      "level": null,
      "parent_id": null,
      "population": 2043,
      "latitude": "35.05515000",
      "longitude": "33.78388000",
      "timezone": "Asia/Famagusta",
      "wikiDataId": "Q81490",
      "country_code": "CY",
      "state_code": "04",
      "state_id": 749,
      "country_id": 57
    },
    {
      "id": 22014,
      "name": "Муниципалитет Аммохостос",
      "name_default": "Ammochostos",
      "native": "Δήμος Αμμοχώστου",
      "type": "municipality",
      "level": null,
      "parent_id": null,
      "population": null,
      "latitude": "35.11755000",
      "longitude": "33.94335000",
      "timezone": "Asia/Famagusta",
      "wikiDataId": "Q56118759",
      "country_code": "CY",
      "state_code": "04",
      "state_id": 749,
      "country_id": 57
    },
    {
      "id": 22020,
      "name": "Авгуроу",
      "name_default": "Avgórou",
      "native": "Αυγόρου",
      "type": "city",
      "level": null,
      "parent_id": null,
      "population": 4604,
      "latitude": "35.03615000",
      "longitude": "33.83918000",
      "timezone": "Asia/Famagusta",
      "wikiDataId": "Q3560533",
      "country_code": "CY",
      "state_code": "04",
      "state_id": 749,
      "country_id": 57
    },
    {
      "id": 22021,
      "name": "Айя-Напа",
      "name_default": "Ayia Napa",
      "native": "Αγία Νάπα",
      "type": "city",
      "level": null,
      "parent_id": null,
      "population": 4717,
      "latitude": "34.98213000",
      "longitude": "34.00183000",
      "timezone": "Asia/Famagusta",
      "wikiDataId": "Q393593",
      "country_code": "CY",
      "state_code": "04",
      "state_id": 749,
      "country_id": 57
    },
    {
      "id": 22023,
      "name": "Дериния",
      "name_default": "Derýneia",
      "native": "Δερύνεια",
      "type": "city",
      "level": null,
      "parent_id": null,
      "population": 5844,
      "latitude": "35.06484000",
      "longitude": "33.96083000",
      "timezone": "Asia/Famagusta",
      "wikiDataId": "Q777760",
      "country_code": "CY",
      "state_code": "04",
      "state_id": 749,
      "country_id": 57
    },
    {
      "id": 22029,
      "name": "Фамагуста",
      "name_default": "Famagusta",
      "native": "Αμμόχωστος",
      "type": "adm1",
      "level": null,
      "parent_id": null,
      "population": 40920,
      "latitude": "35.12054000",
      "longitude": "33.93894000",
      "timezone": "Asia/Famagusta",
      "wikiDataId": "Q193190",
      "country_code": "CY",
      "state_code": "04",
      "state_id": 749,
      "country_id": 57
    },
    {
      "id": 22030,
      "name": "Френарос",
      "name_default": "Frénaros",
      "native": "Φρέναρος",
      "type": "city",
      "level": null,
      "parent_id": null,
      "population": 4298,
      "latitude": "35.04121000",
      "longitude": "33.92242000",
      "timezone": "Asia/Famagusta",
      "wikiDataId": "Q1455222",
      "country_code": "CY",
      "state_code": "04",
      "state_id": 749,
      "country_id": 57
    },
    {
      "id": 22052,
      "name": "Лефконойко",
      "name_default": "Lefkónoiko",
      "native": "Λευκόνοικο",
      "type": "city",
      "level": null,
      "parent_id": null,
      "population": 3187,
      "latitude": "35.25980000",
      "longitude": "33.73189000",
      "timezone": "Asia/Famagusta",
      "wikiDataId": "Q171882",
      "country_code": "CY",
      "state_code": "04",
      "state_id": 749,
      "country_id": 57
    },
    {
      "id": 22054,
      "name": "Леонарисо",
      "name_default": "Leonárisso",
      "native": "Λεονάρισο",
      "type": "city",
      "level": null,
      "parent_id": null,
      "population": 1593,
      "latitude": "35.46892000",
      "longitude": "34.13886000",
      "timezone": "Asia/Famagusta",
      "wikiDataId": "Q28870916",
      "country_code": "CY",
      "state_code": "04",
      "state_id": 749,
      "country_id": 57
    },
    {
      "id": 22056,
      "name": "Лиопетри",
      "name_default": "Liopétri",
      "native": "Λιοπέτρι",
      "type": "city",
      "level": null,
      "parent_id": null,
      "population": 4591,
      "latitude": "35.00885000",
      "longitude": "33.89256000",
      "timezone": "Asia/Famagusta",
      "wikiDataId": "Q546060",
      "country_code": "CY",
      "state_code": "04",
      "state_id": 749,
      "country_id": 57
    },
    {
      "id": 22072,
      "name": "Паралимни",
      "name_default": "Paralímni",
      "native": "Παραλίμνι",
      "type": "city",
      "level": null,
      "parent_id": null,
      "population": 11836,
      "latitude": "35.03945000",
      "longitude": "33.98181000",
      "timezone": "Asia/Famagusta",
      "wikiDataId": "Q954174",
      "country_code": "CY",
      "state_code": "04",
      "state_id": 749,
      "country_id": 57
    },
    {
      "id": 22078,
      "name": "Протарас",
      "name_default": "Protaras",
      "native": "Πρωταράς",
      "type": "city",
      "level": null,
      "parent_id": null,
      "population": 20230,
      "latitude": "35.01250000",
      "longitude": "34.05833000",
      "timezone": "Asia/Famagusta",
      "wikiDataId": "Q2113430",
      "country_code": "CY",
      "state_code": "04",
      "state_id": 749,
      "country_id": 57
    },
    {
      "id": 22090,
      "name": "Ризокарпасо",
      "name_default": "Rizokárpaso",
      "native": "Ριζοκάρπασο",
      "type": "city",
      "level": null,
      "parent_id": null,
      "population": 5215,
      "latitude": "35.59719000",
      "longitude": "34.37916000",
      "timezone": "Asia/Famagusta",
      "wikiDataId": "Q1968566",
      "country_code": "CY",
      "state_code": "04",
      "state_id": 749,
      "country_id": 57
    },
    {
      "id": 22095,
      "name": "Трикомо",
      "name_default": "Tríkomo",
      "native": "Τρίκομο",
      "type": "city",
      "level": null,
      "parent_id": null,
      "population": 4490,
      "latitude": "35.28628000",
      "longitude": "33.89167000",
      "timezone": "Asia/Famagusta",
      "wikiDataId": "Q7846552",
      "country_code": "CY",
      "state_code": "04",
      "state_id": 749,
      "country_id": 57
    }
  ]
}
