{
  "locale": "ja",
  "country": {
    "id": 199,
    "code": "SG",
    "iso3": "SGP",
    "numeric_code": "702",
    "name": "シンガポール",
    "name_default": "Singapore",
    "native": "Singapore",
    "capital": "Singapur",
    "phonecode": "65",
    "currency": "SGD",
    "currency_name": "Singapore dollar",
    "currency_symbol": "$",
    "tld": ".sg",
    "population": 6036900,
    "gdp": 564774,
    "region": "Asia",
    "region_id": 3,
    "subregion": "South-Eastern Asia",
    "subregion_id": 13,
    "nationality": "Singaporean",
    "timezones": [
      {
        "zoneName": "Asia/Singapore",
        "gmtOffset": 28800,
        "gmtOffsetName": "UTC+08:00",
        "abbreviation": "SGT",
        "tzName": "Singapore Time"
      }
    ],
    "latitude": "1.36666666",
    "longitude": "103.80000000",
    "emoji": "🇸🇬",
    "emojiU": "U+1F1F8 U+1F1EC"
  },
  "state": {
    "id": 4652,
    "code": "05",
    "iso2": "05",
    "iso3166_2": "SG-05",
    "fips_code": "79",
    "name": "南西",
    "name_default": "South West",
    "native": "South West",
    "type": "district",
    "level": null,
    "parent_id": null,
    "population": null,
    "latitude": "5.28833890",
    "longitude": "100.28150990",
    "timezone": "Asia/Singapore",
    "wikiDataId": "Q5784126",
    "country_code": "SG"
  },
  "cities": [
    {
      "id": 153481,
      "name": "ブキット・バトック",
      "name_default": "Bukit Batok",
      "native": "Bukit Batok",
      "type": "section",
      "level": null,
      "parent_id": null,
      "population": 11020,
      "latitude": "1.34960000",
      "longitude": "103.75280000",
      "timezone": "Asia/Singapore",
      "wikiDataId": "Q225021",
      "country_code": "SG",
      "state_code": "05",
      "state_id": 4652,
      "country_id": 199
    },
    {
      "id": 153482,
      "name": "ブキット・パンジャン",
      "name_default": "Bukit Panjang",
      "native": "Long hill",
      "type": "section",
      "level": null,
      "parent_id": null,
      "population": 29960,
      "latitude": "1.37860000",
      "longitude": "103.76260000",
      "timezone": "Asia/Singapore",
      "wikiDataId": "Q199242",
      "country_code": "SG",
      "state_code": "05",
      "state_id": 4652,
      "country_id": 199
    },
    {
      "id": 153480,
      "name": "ジュロン・ウェスト",
      "name_default": "Jurong West",
      "native": "Jurong West",
      "type": "city",
      "level": null,
      "parent_id": null,
      "population": 257470,
      "latitude": "1.33960000",
      "longitude": "103.70730000",
      "timezone": "Asia/Singapore",
      "wikiDataId": "Q190717",
      "country_code": "SG",
      "state_code": "05",
      "state_id": 4652,
      "country_id": 199
    }
  ]
}
