{
  "locale": "hi",
  "country": {
    "id": 235,
    "code": "UY",
    "iso3": "URY",
    "numeric_code": "858",
    "name": "उरुग्वे",
    "name_default": "Uruguay",
    "native": "Uruguay",
    "capital": "Montevideo",
    "phonecode": "598",
    "currency": "UYU",
    "currency_name": "Uruguayan peso",
    "currency_symbol": "$",
    "tld": ".uy",
    "population": 3499451,
    "gdp": 79731,
    "region": "Americas",
    "region_id": 2,
    "subregion": "South America",
    "subregion_id": 8,
    "nationality": "Uruguayan",
    "timezones": [
      {
        "zoneName": "America/Montevideo",
        "gmtOffset": -10800,
        "gmtOffsetName": "UTC-03:00",
        "abbreviation": "UYT",
        "tzName": "Uruguay Standard Time"
      }
    ],
    "latitude": "-33.00000000",
    "longitude": "-56.00000000",
    "emoji": "🇺🇾",
    "emojiU": "U+1F1FA U+1F1FE"
  },
  "state": {
    "id": 3220,
    "code": "SA",
    "iso2": "SA",
    "iso3166_2": "UY-SA",
    "fips_code": "15",
    "name": "साल्टो",
    "name_default": "Salto",
    "native": "Tacón",
    "type": "department",
    "level": null,
    "parent_id": null,
    "population": null,
    "latitude": "-31.38802800",
    "longitude": "-57.96124550",
    "timezone": "America/Montevideo",
    "wikiDataId": "Q16595",
    "country_code": "UY"
  },
  "cities": [
    {
      "id": 129783,
      "name": "बेलें",
      "name_default": "Belén",
      "native": "Belén",
      "type": "city",
      "level": null,
      "parent_id": null,
      "population": 1926,
      "latitude": "-30.78716000",
      "longitude": "-57.77577000",
      "timezone": "America/Montevideo",
      "wikiDataId": "Q816336",
      "country_code": "UY",
      "state_code": "SA",
      "state_id": 3220,
      "country_id": 235
    },
    {
      "id": 129857,
      "name": "साल्टो",
      "name_default": "Salto",
      "native": "Tacón",
      "type": "adm1",
      "level": null,
      "parent_id": null,
      "population": 124878,
      "latitude": "-31.38333000",
      "longitude": "-57.96667000",
      "timezone": "America/Montevideo",
      "wikiDataId": "Q335506",
      "country_code": "UY",
      "state_code": "SA",
      "state_id": 3220,
      "country_id": 235
    },
    {
      "id": 129889,
      "name": "विला कॉन्स्टिट्यूसिओन",
      "name_default": "Villa Constitución",
      "native": "Villa Constitución",
      "type": "city",
      "level": null,
      "parent_id": null,
      "population": 2846,
      "latitude": "-31.06913000",
      "longitude": "-57.84946000",
      "timezone": "America/Montevideo",
      "wikiDataId": "Q1128223",
      "country_code": "UY",
      "state_code": "SA",
      "state_id": 3220,
      "country_id": 235
    }
  ]
}
