{
  "locale": "nl",
  "country": {
    "id": 58,
    "code": "CZ",
    "iso3": "CZE",
    "numeric_code": "203",
    "name": "Tsjechië",
    "name_default": "Czech Republic",
    "native": "Česká republika",
    "capital": "Prague",
    "phonecode": "420",
    "currency": "CZK",
    "currency_name": "Czech koruna",
    "currency_symbol": "Kč",
    "tld": ".cz",
    "population": 10876875,
    "gdp": 360244,
    "region": "Europe",
    "region_id": 4,
    "subregion": "Eastern Europe",
    "subregion_id": 15,
    "nationality": "Czech",
    "timezones": [
      {
        "zoneName": "Europe/Prague",
        "gmtOffset": 3600,
        "gmtOffsetName": "UTC+01:00",
        "abbreviation": "CET",
        "tzName": "Central European Time"
      }
    ],
    "latitude": "49.75000000",
    "longitude": "15.50000000",
    "emoji": "🇨🇿",
    "emojiU": "U+1F1E8 U+1F1FF"
  },
  "state": {
    "id": 4639,
    "code": "31",
    "iso2": "31",
    "iso3166_2": "CZ-31",
    "fips_code": "79",
    "name": "Jihočeský kraj",
    "name_default": "Jihočeský kraj",
    "native": "Jihočeský kraj",
    "type": "region",
    "level": null,
    "parent_id": null,
    "population": 654505,
    "latitude": "49.08645480",
    "longitude": "14.60017270",
    "timezone": "Europe/Prague",
    "wikiDataId": "Q188373",
    "country_code": "CZ"
  },
  "cities": [
    {
      "id": 22115,
      "name": "Bavorov",
      "name_default": "Bavorov",
      "native": "Bavor",
      "type": "city",
      "level": null,
      "parent_id": null,
      "population": 1683,
      "latitude": "49.12184000",
      "longitude": "14.07893000",
      "timezone": "Europe/Prague",
      "wikiDataId": "Q791533",
      "country_code": "CZ",
      "state_code": "31",
      "state_id": 4639,
      "country_id": 58
    },
    {
      "id": 22118,
      "name": "Bechyně",
      "name_default": "Bechyně",
      "native": "Bechyně",
      "type": "city",
      "level": null,
      "parent_id": null,
      "population": 4815,
      "latitude": "49.29523000",
      "longitude": "14.46810000",
      "timezone": "Europe/Prague",
      "wikiDataId": "Q20492",
      "country_code": "CZ",
      "state_code": "31",
      "state_id": 4639,
      "country_id": 58
    },
    {
      "id": 22123,
      "name": "Benešov nad Černou",
      "name_default": "Benešov nad Černou",
      "native": "Benešov nad Černou",
      "type": "city",
      "level": null,
      "parent_id": null,
      "population": 1259,
      "latitude": "48.72940000",
      "longitude": "14.62737000",
      "timezone": "Europe/Prague",
      "wikiDataId": "Q817143",
      "country_code": "CZ",
      "state_code": "31",
      "state_id": 4639,
      "country_id": 58
    },
    {
      "id": 22125,
      "name": "Bernartice",
      "name_default": "Bernartice",
      "native": "Bernartice",
      "type": "city",
      "level": null,
      "parent_id": null,
      "population": 1405,
      "latitude": "49.36889000",
      "longitude": "14.38101000",
      "timezone": "Europe/Prague",
      "wikiDataId": "Q823134",
      "country_code": "CZ",
      "state_code": "31",
      "state_id": 4639,
      "country_id": 58
    },
    {
      "id": 22130,
      "name": "Blatná",
      "name_default": "Blatná",
      "native": "Blatná",
      "type": "city",
      "level": null,
      "parent_id": null,
      "population": 6669,
      "latitude": "49.42489000",
      "longitude": "13.88176000",
      "timezone": "Europe/Prague",
      "wikiDataId": "Q804395",
      "country_code": "CZ",
      "state_code": "31",
      "state_id": 4639,
      "country_id": 58
    },
    {
      "id": 22147,
      "name": "Borek",
      "name_default": "Borek",
      "native": "BORK",
      "type": "city",
      "level": null,
      "parent_id": null,
      "population": 1157,
      "latitude": "49.02339000",
      "longitude": "14.50088000",
      "timezone": "Europe/Prague",
      "wikiDataId": "Q893488",
      "country_code": "CZ",
      "state_code": "31",
      "state_id": 4639,
      "country_id": 58
    },
    {
      "id": 22150,
      "name": "Borová Lada",
      "name_default": "Borová Lada",
      "native": "Borová Lada",
      "type": "adm3",
      "level": null,
      "parent_id": null,
      "population": 276,
      "latitude": "48.98983000",
      "longitude": "13.65986000",
      "timezone": "Europe/Prague",
      "wikiDataId": "Q835344",
      "country_code": "CZ",
      "state_code": "31",
      "state_id": 4639,
      "country_id": 58
    },
    {
      "id": 22149,
      "name": "Borovany",
      "name_default": "Borovany",
      "native": "Borovany",
      "type": "city",
      "level": null,
      "parent_id": null,
      "population": 4184,
      "latitude": "48.89860000",
      "longitude": "14.64227000",
      "timezone": "Europe/Prague",
      "wikiDataId": "Q894102",
      "country_code": "CZ",
      "state_code": "31",
      "state_id": 4639,
      "country_id": 58
    },
    {
      "id": 22164,
      "name": "Brloh",
      "name_default": "Brloh",
      "native": "Broloh",
      "type": "city",
      "level": null,
      "parent_id": null,
      "population": 1039,
      "latitude": "48.92987000",
      "longitude": "14.21857000",
      "timezone": "Europe/Prague",
      "wikiDataId": "Q921730",
      "country_code": "CZ",
      "state_code": "31",
      "state_id": 4639,
      "country_id": 58
    },
    {
      "id": 23388,
      "name": "České Budějovice",
      "name_default": "České Budějovice",
      "native": "České Budějovice",
      "type": "adm1",
      "level": null,
      "parent_id": null,
      "population": 97231,
      "latitude": "48.97447000",
      "longitude": "14.47434000",
      "timezone": "Europe/Prague",
      "wikiDataId": "Q16506",
      "country_code": "CZ",
      "state_code": "31",
      "state_id": 4639,
      "country_id": 58
    },
    {
      "id": 23390,
      "name": "České Velenice",
      "name_default": "České Velenice",
      "native": "České Velenice",
      "type": "city",
      "level": null,
      "parent_id": null,
      "population": 3607,
      "latitude": "48.76851000",
      "longitude": "14.96368000",
      "timezone": "Europe/Prague",
      "wikiDataId": "Q341197",
      "country_code": "CZ",
      "state_code": "31",
      "state_id": 4639,
      "country_id": 58
    },
    {
      "id": 23393,
      "name": "Český Krumlov",
      "name_default": "Český Krumlov",
      "native": "Český Krumlov",
      "type": "city",
      "level": null,
      "parent_id": null,
      "population": 12797,
      "latitude": "48.81091000",
      "longitude": "14.31521000",
      "timezone": "Europe/Prague",
      "wikiDataId": "Q188082",
      "country_code": "CZ",
      "state_code": "31",
      "state_id": 4639,
      "country_id": 58
    },
    {
      "id": 23394,
      "name": "Český Rudolec",
      "name_default": "Český Rudolec",
      "native": "Český Rudolec",
      "type": "city",
      "level": null,
      "parent_id": null,
      "population": 1004,
      "latitude": "49.06835000",
      "longitude": "15.32437000",
      "timezone": "Europe/Prague",
      "wikiDataId": "Q341258",
      "country_code": "CZ",
      "state_code": "31",
      "state_id": 4639,
      "country_id": 58
    },
    {
      "id": 22219,
      "name": "Chlum u Třeboně",
      "name_default": "Chlum u Třeboně",
      "native": "Chlum u Třeboně",
      "type": "city",
      "level": null,
      "parent_id": null,
      "population": 1816,
      "latitude": "48.96235000",
      "longitude": "14.92799000",
      "timezone": "Europe/Prague",
      "wikiDataId": "Q265518",
      "country_code": "CZ",
      "state_code": "31",
      "state_id": 4639,
      "country_id": 58
    },
    {
      "id": 22227,
      "name": "Chotoviny",
      "name_default": "Chotoviny",
      "native": "Chotoness",
      "type": "city",
      "level": null,
      "parent_id": null,
      "population": 1783,
      "latitude": "49.47803000",
      "longitude": "14.67695000",
      "timezone": "Europe/Prague",
      "wikiDataId": "Q1076706",
      "country_code": "CZ",
      "state_code": "31",
      "state_id": 4639,
      "country_id": 58
    },
    {
      "id": 22240,
      "name": "Chvalšiny",
      "name_default": "Chvalšiny",
      "native": "Chvalšiny",
      "type": "city",
      "level": null,
      "parent_id": null,
      "population": 1244,
      "latitude": "48.85401000",
      "longitude": "14.21114000",
      "timezone": "Europe/Prague",
      "wikiDataId": "Q1090156",
      "country_code": "CZ",
      "state_code": "31",
      "state_id": 4639,
      "country_id": 58
    },
    {
      "id": 22243,
      "name": "Chýnov",
      "name_default": "Chýnov",
      "native": "Modřiny",
      "type": "city",
      "level": null,
      "parent_id": null,
      "population": 2568,
      "latitude": "49.40677000",
      "longitude": "14.81122000",
      "timezone": "Europe/Prague",
      "wikiDataId": "Q1018863",
      "country_code": "CZ",
      "state_code": "31",
      "state_id": 4639,
      "country_id": 58
    },
    {
      "id": 22242,
      "name": "Chyšky",
      "name_default": "Chyšky",
      "native": "Chyšky",
      "type": "city",
      "level": null,
      "parent_id": null,
      "population": 1066,
      "latitude": "49.52346000",
      "longitude": "14.42757000",
      "timezone": "Europe/Prague",
      "wikiDataId": "Q939648",
      "country_code": "CZ",
      "state_code": "31",
      "state_id": 4639,
      "country_id": 58
    },
    {
      "id": 23396,
      "name": "Čimelice",
      "name_default": "Čimelice",
      "native": "Kuřata",
      "type": "city",
      "level": null,
      "parent_id": null,
      "population": 1045,
      "latitude": "49.46557000",
      "longitude": "14.06922000",
      "timezone": "Europe/Prague",
      "wikiDataId": "Q1925206",
      "country_code": "CZ",
      "state_code": "31",
      "state_id": 4639,
      "country_id": 58
    },
    {
      "id": 23397,
      "name": "Čkyně",
      "name_default": "Čkyně",
      "native": "Čkyně",
      "type": "city",
      "level": null,
      "parent_id": null,
      "population": 1616,
      "latitude": "49.11503000",
      "longitude": "13.82906000",
      "timezone": "Europe/Prague",
      "wikiDataId": "Q341607",
      "country_code": "CZ",
      "state_code": "31",
      "state_id": 4639,
      "country_id": 58
    },
    {
      "id": 22252,
      "name": "Dačice",
      "name_default": "Dačice",
      "native": "Dačice",
      "type": "city",
      "level": null,
      "parent_id": null,
      "population": 7157,
      "latitude": "49.08154000",
      "longitude": "15.43727000",
      "timezone": "Europe/Prague",
      "wikiDataId": "Q1013843",
      "country_code": "CZ",
      "state_code": "31",
      "state_id": 4639,
      "country_id": 58
    },
    {
      "id": 22277,
      "name": "Dolní Bukovsko",
      "name_default": "Dolní Bukovsko",
      "native": "Dolní Bukovsko",
      "type": "city",
      "level": null,
      "parent_id": null,
      "population": 1712,
      "latitude": "49.17086000",
      "longitude": "14.58127000",
      "timezone": "Europe/Prague",
      "wikiDataId": "Q1146788",
      "country_code": "CZ",
      "state_code": "31",
      "state_id": 4639,
      "country_id": 58
    },
    {
      "id": 22282,
      "name": "Dolní Dvořiště",
      "name_default": "Dolní Dvořiště",
      "native": "Dolní Dvořiště",
      "type": "city",
      "level": null,
      "parent_id": null,
      "population": 1388,
      "latitude": "48.65642000",
      "longitude": "14.45221000",
      "timezone": "Europe/Prague",
      "wikiDataId": "Q527002",
      "country_code": "CZ",
      "state_code": "31",
      "state_id": 4639,
      "country_id": 58
    },
    {
      "id": 22324,
      "name": "Dřiteň",
      "name_default": "Dřiteň",
      "native": "Dřiteň",
      "type": "city",
      "level": null,
      "parent_id": null,
      "population": 1392,
      "latitude": "49.14280000",
      "longitude": "14.34596000",
      "timezone": "Europe/Prague",
      "wikiDataId": "Q1272769",
      "country_code": "CZ",
      "state_code": "31",
      "state_id": 4639,
      "country_id": 58
    },
    {
      "id": 22313,
      "name": "Dubné",
      "name_default": "Dubné",
      "native": "Dubné",
      "type": "city",
      "level": null,
      "parent_id": null,
      "population": 1141,
      "latitude": "48.97619000",
      "longitude": "14.36038000",
      "timezone": "Europe/Prague",
      "wikiDataId": "Q2500110",
      "country_code": "CZ",
      "state_code": "31",
      "state_id": 4639,
      "country_id": 58
    },
    {
      "id": 22328,
      "name": "Frymburk",
      "name_default": "Frymburk",
      "native": "Frymburk",
      "type": "city",
      "level": null,
      "parent_id": null,
      "population": 1355,
      "latitude": "48.66094000",
      "longitude": "14.16564000",
      "timezone": "Europe/Prague",
      "wikiDataId": "Q164536",
      "country_code": "CZ",
      "state_code": "31",
      "state_id": 4639,
      "country_id": 58
    },
    {
      "id": 22355,
      "name": "Hluboká nad Vltavou",
      "name_default": "Hluboká nad Vltavou",
      "native": "Hluboká nad Vltavou",
      "type": "city",
      "level": null,
      "parent_id": null,
      "population": 5626,
      "latitude": "49.05225000",
      "longitude": "14.43427000",
      "timezone": "Europe/Prague",
      "wikiDataId": "Q1010144",
      "country_code": "CZ",
      "state_code": "31",
      "state_id": 4639,
      "country_id": 58
    },
    {
      "id": 22385,
      "name": "Horní Planá",
      "name_default": "Horní Planá",
      "native": "Horní Planá",
      "type": "city",
      "level": null,
      "parent_id": null,
      "population": 1943,
      "latitude": "48.76736000",
      "longitude": "14.03257000",
      "timezone": "Europe/Prague",
      "wikiDataId": "Q1628741",
      "country_code": "CZ",
      "state_code": "31",
      "state_id": 4639,
      "country_id": 58
    },
    {
      "id": 22390,
      "name": "Horní Stropnice",
      "name_default": "Horní Stropnice",
      "native": "Horní Stropnice",
      "type": "city",
      "level": null,
      "parent_id": null,
      "population": 1560,
      "latitude": "48.76124000",
      "longitude": "14.73502000",
      "timezone": "Europe/Prague",
      "wikiDataId": "Q1487640",
      "country_code": "CZ",
      "state_code": "31",
      "state_id": 4639,
      "country_id": 58
    },
    {
      "id": 22418,
      "name": "Hrdějovice",
      "name_default": "Hrdějovice",
      "native": "Hrdějovice",
      "type": "city",
      "level": null,
      "parent_id": null,
      "population": 1560,
      "latitude": "49.01893000",
      "longitude": "14.47857000",
      "timezone": "Europe/Prague",
      "wikiDataId": "Q1632399",
      "country_code": "CZ",
      "state_code": "31",
      "state_id": 4639,
      "country_id": 58
    },
    {
      "id": 22436,
      "name": "Husinec",
      "name_default": "Husinec",
      "native": "Husin",
      "type": "city",
      "level": null,
      "parent_id": null,
      "population": 1405,
      "latitude": "49.05496000",
      "longitude": "13.98697000",
      "timezone": "Europe/Prague",
      "wikiDataId": "Q1638949",
      "country_code": "CZ",
      "state_code": "31",
      "state_id": 4639,
      "country_id": 58
    },
    {
      "id": 22460,
      "name": "Jarošov nad Nežárkou",
      "name_default": "Jarošov nad Nežárkou",
      "native": "Jarošov nad Nežárkou",
      "type": "city",
      "level": null,
      "parent_id": null,
      "population": 1067,
      "latitude": "49.18989000",
      "longitude": "15.06734000",
      "timezone": "Europe/Prague",
      "wikiDataId": "Q1683695",
      "country_code": "CZ",
      "state_code": "31",
      "state_id": 4639,
      "country_id": 58
    },
    {
      "id": 22476,
      "name": "Jindřichův Hradec",
      "name_default": "Jindřichův Hradec",
      "native": "Jindřichův Hradec",
      "type": "city",
      "level": null,
      "parent_id": null,
      "population": 20540,
      "latitude": "49.14404000",
      "longitude": "15.00301000",
      "timezone": "Europe/Prague",
      "wikiDataId": "Q368929",
      "country_code": "CZ",
      "state_code": "31",
      "state_id": 4639,
      "country_id": 58
    },
    {
      "id": 22479,
      "name": "Jistebnice",
      "name_default": "Jistebnice",
      "native": "Jistebnice",
      "type": "city",
      "level": null,
      "parent_id": null,
      "population": 2132,
      "latitude": "49.48553000",
      "longitude": "14.52760000",
      "timezone": "Europe/Prague",
      "wikiDataId": "Q2702822",
      "country_code": "CZ",
      "state_code": "31",
      "state_id": 4639,
      "country_id": 58
    },
    {
      "id": 22582,
      "name": "Kájov",
      "name_default": "Kájov",
      "native": "Kajov",
      "type": "city",
      "level": null,
      "parent_id": null,
      "population": 1870,
      "latitude": "48.81082000",
      "longitude": "14.25859000",
      "timezone": "Europe/Prague",
      "wikiDataId": "Q1795250",
      "country_code": "CZ",
      "state_code": "31",
      "state_id": 4639,
      "country_id": 58
    },
    {
      "id": 22494,
      "name": "Kamenný Újezd",
      "name_default": "Kamenný Újezd",
      "native": "Kamenný Újezd",
      "type": "city",
      "level": null,
      "parent_id": null,
      "population": 2002,
      "latitude": "48.89753000",
      "longitude": "14.44638000",
      "timezone": "Europe/Prague",
      "wikiDataId": "Q1306068",
      "country_code": "CZ",
      "state_code": "31",
      "state_id": 4639,
      "country_id": 58
    },
    {
      "id": 22495,
      "name": "Kaplice",
      "name_default": "Kaplice",
      "native": "Kaple",
      "type": "city",
      "level": null,
      "parent_id": null,
      "population": 7531,
      "latitude": "48.73881000",
      "longitude": "14.49449000",
      "timezone": "Europe/Prague",
      "wikiDataId": "Q954808",
      "country_code": "CZ",
      "state_code": "31",
      "state_id": 4639,
      "country_id": 58
    },
    {
      "id": 22496,
      "name": "Kardašova Řečice",
      "name_default": "Kardašova Řečice",
      "native": "Kardašova Řečice",
      "type": "city",
      "level": null,
      "parent_id": null,
      "population": 2221,
      "latitude": "49.18478000",
      "longitude": "14.85315000",
      "timezone": "Europe/Prague",
      "wikiDataId": "Q1729076",
      "country_code": "CZ",
      "state_code": "31",
      "state_id": 4639,
      "country_id": 58
    },
    {
      "id": 22503,
      "name": "Katovice",
      "name_default": "Katovice",
      "native": "Katovice",
      "type": "city",
      "level": null,
      "parent_id": null,
      "population": 1331,
      "latitude": "49.27348000",
      "longitude": "13.83035000",
      "timezone": "Europe/Prague",
      "wikiDataId": "Q1088443",
      "country_code": "CZ",
      "state_code": "31",
      "state_id": 4639,
      "country_id": 58
    },
    {
      "id": 22545,
      "name": "Kovářov",
      "name_default": "Kovářov",
      "native": "Kovářov",
      "type": "city",
      "level": null,
      "parent_id": null,
      "population": 1465,
      "latitude": "49.51760000",
      "longitude": "14.27809000",
      "timezone": "Europe/Prague",
      "wikiDataId": "Q2254971",
      "country_code": "CZ",
      "state_code": "31",
      "state_id": 4639,
      "country_id": 58
    },
    {
      "id": 22583,
      "name": "Křemže",
      "name_default": "Křemže",
      "native": "Křemže",
      "type": "city",
      "level": null,
      "parent_id": null,
      "population": 2989,
      "latitude": "48.90497000",
      "longitude": "14.30568000",
      "timezone": "Europe/Prague",
      "wikiDataId": "Q651930",
      "country_code": "CZ",
      "state_code": "31",
      "state_id": 4639,
      "country_id": 58
    },
    {
      "id": 22575,
      "name": "Kunžak",
      "name_default": "Kunžak",
      "native": "Raby",
      "type": "city",
      "level": null,
      "parent_id": null,
      "population": 1484,
      "latitude": "49.12119000",
      "longitude": "15.19028000",
      "timezone": "Europe/Prague",
      "wikiDataId": "Q1648013",
      "country_code": "CZ",
      "state_code": "31",
      "state_id": 4639,
      "country_id": 58
    },
    {
      "id": 22592,
      "name": "Ledenice",
      "name_default": "Ledenice",
      "native": "Ledovce",
      "type": "city",
      "level": null,
      "parent_id": null,
      "population": 2544,
      "latitude": "48.93329000",
      "longitude": "14.61886000",
      "timezone": "Europe/Prague",
      "wikiDataId": "Q1811531",
      "country_code": "CZ",
      "state_code": "31",
      "state_id": 4639,
      "country_id": 58
    },
    {
      "id": 22603,
      "name": "Lhenice",
      "name_default": "Lhenice",
      "native": "Lhenice",
      "type": "city",
      "level": null,
      "parent_id": null,
      "population": 2052,
      "latitude": "48.99479000",
      "longitude": "14.14980000",
      "timezone": "Europe/Prague",
      "wikiDataId": "Q1822500",
      "country_code": "CZ",
      "state_code": "31",
      "state_id": 4639,
      "country_id": 58
    },
    {
      "id": 22627,
      "name": "Lišov",
      "name_default": "Lišov",
      "native": "Lišov",
      "type": "city",
      "level": null,
      "parent_id": null,
      "population": 4679,
      "latitude": "49.01597000",
      "longitude": "14.60838000",
      "timezone": "Europe/Prague",
      "wikiDataId": "Q1564700",
      "country_code": "CZ",
      "state_code": "31",
      "state_id": 4639,
      "country_id": 58
    },
    {
      "id": 22626,
      "name": "Litvínovice",
      "name_default": "Litvínovice",
      "native": "Litvínovice",
      "type": "city",
      "level": null,
      "parent_id": null,
      "population": 1483,
      "latitude": "48.96207000",
      "longitude": "14.45146000",
      "timezone": "Europe/Prague",
      "wikiDataId": "Q1866020",
      "country_code": "CZ",
      "state_code": "31",
      "state_id": 4639,
      "country_id": 58
    },
    {
      "id": 22634,
      "name": "Lomnice nad Lužnicí",
      "name_default": "Lomnice nad Lužnicí",
      "native": "Lomnice nad Lužnicí",
      "type": "city",
      "level": null,
      "parent_id": null,
      "population": 1778,
      "latitude": "49.08468000",
      "longitude": "14.71727000",
      "timezone": "Europe/Prague",
      "wikiDataId": "Q1818179",
      "country_code": "CZ",
      "state_code": "31",
      "state_id": 4639,
      "country_id": 58
    },
    {
      "id": 22640,
      "name": "Loučovice",
      "name_default": "Loučovice",
      "native": "Loučovice",
      "type": "city",
      "level": null,
      "parent_id": null,
      "population": 1955,
      "latitude": "48.62019000",
      "longitude": "14.25747000",
      "timezone": "Europe/Prague",
      "wikiDataId": "Q1584350",
      "country_code": "CZ",
      "state_code": "31",
      "state_id": 4639,
      "country_id": 58
    },
    {
      "id": 22670,
      "name": "Malonty",
      "name_default": "Malonty",
      "native": "Maloni",
      "type": "city",
      "level": null,
      "parent_id": null,
      "population": 1135,
      "latitude": "48.68611000",
      "longitude": "14.57678000",
      "timezone": "Europe/Prague",
      "wikiDataId": "Q1778205",
      "country_code": "CZ",
      "state_code": "31",
      "state_id": 4639,
      "country_id": 58
    },
    {
      "id": 22674,
      "name": "Malšice",
      "name_default": "Malšice",
      "native": "Malšice",
      "type": "city",
      "level": null,
      "parent_id": null,
      "population": 1893,
      "latitude": "49.36391000",
      "longitude": "14.57868000",
      "timezone": "Europe/Prague",
      "wikiDataId": "Q2735270",
      "country_code": "CZ",
      "state_code": "31",
      "state_id": 4639,
      "country_id": 58
    },
    {
      "id": 22689,
      "name": "Milevsko",
      "name_default": "Milevsko",
      "native": "Milevsko",
      "type": "city",
      "level": null,
      "parent_id": null,
      "population": 7950,
      "latitude": "49.45089000",
      "longitude": "14.36000000",
      "timezone": "Europe/Prague",
      "wikiDataId": "Q1015011",
      "country_code": "CZ",
      "state_code": "31",
      "state_id": 4639,
      "country_id": 58
    },
    {
      "id": 22696,
      "name": "Mirotice",
      "name_default": "Mirotice",
      "native": "Mirotice",
      "type": "city",
      "level": null,
      "parent_id": null,
      "population": 1232,
      "latitude": "49.42908000",
      "longitude": "14.03697000",
      "timezone": "Europe/Prague",
      "wikiDataId": "Q1641811",
      "country_code": "CZ",
      "state_code": "31",
      "state_id": 4639,
      "country_id": 58
    },
    {
      "id": 22697,
      "name": "Mirovice",
      "name_default": "Mirovice",
      "native": "Mirovice",
      "type": "city",
      "level": null,
      "parent_id": null,
      "population": 1623,
      "latitude": "49.51555000",
      "longitude": "14.03582000",
      "timezone": "Europe/Prague",
      "wikiDataId": "Q1641693",
      "country_code": "CZ",
      "state_code": "31",
      "state_id": 4639,
      "country_id": 58
    },
    {
      "id": 22702,
      "name": "Mladá Vožice",
      "name_default": "Mladá Vožice",
      "native": "Mladá Vožice",
      "type": "city",
      "level": null,
      "parent_id": null,
      "population": 2705,
      "latitude": "49.53313000",
      "longitude": "14.80857000",
      "timezone": "Europe/Prague",
      "wikiDataId": "Q1456612",
      "country_code": "CZ",
      "state_code": "31",
      "state_id": 4639,
      "country_id": 58
    },
    {
      "id": 22762,
      "name": "Netolice",
      "name_default": "Netolice",
      "native": "Blízko Toce",
      "type": "city",
      "level": null,
      "parent_id": null,
      "population": 2467,
      "latitude": "49.04930000",
      "longitude": "14.19700000",
      "timezone": "Europe/Prague",
      "wikiDataId": "Q1531214",
      "country_code": "CZ",
      "state_code": "31",
      "state_id": 4639,
      "country_id": 58
    },
    {
      "id": 22772,
      "name": "Nová Bystřice",
      "name_default": "Nová Bystřice",
      "native": "Nová Bystřice",
      "type": "city",
      "level": null,
      "parent_id": null,
      "population": 3199,
      "latitude": "49.01926000",
      "longitude": "15.10316000",
      "timezone": "Europe/Prague",
      "wikiDataId": "Q1935413",
      "country_code": "CZ",
      "state_code": "31",
      "state_id": 4639,
      "country_id": 58
    },
    {
      "id": 22776,
      "name": "Nová Včelnice",
      "name_default": "Nová Včelnice",
      "native": "Nová Včelnice",
      "type": "city",
      "level": null,
      "parent_id": null,
      "population": 2176,
      "latitude": "49.23935000",
      "longitude": "15.07260000",
      "timezone": "Europe/Prague",
      "wikiDataId": "Q1861156",
      "country_code": "CZ",
      "state_code": "31",
      "state_id": 4639,
      "country_id": 58
    },
    {
      "id": 22777,
      "name": "Nové Hrady",
      "name_default": "Nové Hrady",
      "native": "Nové Hrady",
      "type": "city",
      "level": null,
      "parent_id": null,
      "population": 2469,
      "latitude": "48.78963000",
      "longitude": "14.77839000",
      "timezone": "Europe/Prague",
      "wikiDataId": "Q1019355",
      "country_code": "CZ",
      "state_code": "31",
      "state_id": 4639,
      "country_id": 58
    },
    {
      "id": 22877,
      "name": "Okres České Budějovice",
      "name_default": "Okres České Budějovice",
      "native": "Okres České Budějovice",
      "type": "city",
      "level": null,
      "parent_id": null,
      "population": 202172,
      "latitude": "49.00000000",
      "longitude": "14.50000000",
      "timezone": "Europe/Prague",
      "wikiDataId": "Q753120",
      "country_code": "CZ",
      "state_code": "31",
      "state_id": 4639,
      "country_id": 58
    },
    {
      "id": 22878,
      "name": "Okres Český Krumlov",
      "name_default": "Okres Český Krumlov",
      "native": "Okres Český Krumlov",
      "type": "city",
      "level": null,
      "parent_id": null,
      "population": 61655,
      "latitude": "48.75000000",
      "longitude": "14.33333000",
      "timezone": "Europe/Prague",
      "wikiDataId": "Q605208",
      "country_code": "CZ",
      "state_code": "31",
      "state_id": 4639,
      "country_id": 58
    },
    {
      "id": 22824,
      "name": "Okres Jindřichův Hradec",
      "name_default": "Okres Jindřichův Hradec",
      "native": "Okres Jindřichův Hradec",
      "type": "city",
      "level": null,
      "parent_id": null,
      "population": 89564,
      "latitude": "49.08333000",
      "longitude": "15.16667000",
      "timezone": "Europe/Prague",
      "wikiDataId": "Q1160841",
      "country_code": "CZ",
      "state_code": "31",
      "state_id": 4639,
      "country_id": 58
    },
    {
      "id": 22854,
      "name": "Okres Písek",
      "name_default": "Okres Písek",
      "native": "Okres Písek",
      "type": "city",
      "level": null,
      "parent_id": null,
      "population": 72912,
      "latitude": "49.40000000",
      "longitude": "14.20000000",
      "timezone": "Europe/Prague",
      "wikiDataId": "Q594929",
      "country_code": "CZ",
      "state_code": "31",
      "state_id": 4639,
      "country_id": 58
    },
    {
      "id": 22850,
      "name": "Okres Prachatice",
      "name_default": "Okres Prachatice",
      "native": "Okres Prachatice",
      "type": "city",
      "level": null,
      "parent_id": null,
      "population": 51061,
      "latitude": "49.00000000",
      "longitude": "13.86667000",
      "timezone": "Europe/Prague",
      "wikiDataId": "Q385016",
      "country_code": "CZ",
      "state_code": "31",
      "state_id": 4639,
      "country_id": 58
    },
    {
      "id": 22862,
      "name": "Okres Strakonice",
      "name_default": "Okres Strakonice",
      "native": "Okres Strakonice",
      "type": "city",
      "level": null,
      "parent_id": null,
      "population": 71602,
      "latitude": "49.26667000",
      "longitude": "13.90000000",
      "timezone": "Europe/Prague",
      "wikiDataId": "Q837633",
      "country_code": "CZ",
      "state_code": "31",
      "state_id": 4639,
      "country_id": 58
    },
    {
      "id": 22867,
      "name": "Okres Tábor",
      "name_default": "Okres Tábor",
      "native": "County Tabor",
      "type": "city",
      "level": null,
      "parent_id": null,
      "population": 104261,
      "latitude": "49.41667000",
      "longitude": "14.66667000",
      "timezone": "Europe/Prague",
      "wikiDataId": "Q117503",
      "country_code": "CZ",
      "state_code": "31",
      "state_id": 4639,
      "country_id": 58
    },
    {
      "id": 22893,
      "name": "Opařany",
      "name_default": "Opařany",
      "native": "Opařany",
      "type": "city",
      "level": null,
      "parent_id": null,
      "population": 1365,
      "latitude": "49.39678000",
      "longitude": "14.48137000",
      "timezone": "Europe/Prague",
      "wikiDataId": "Q1674877",
      "country_code": "CZ",
      "state_code": "31",
      "state_id": 4639,
      "country_id": 58
    },
    {
      "id": 22993,
      "name": "Písek",
      "name_default": "Písek",
      "native": "Písek",
      "type": "city",
      "level": null,
      "parent_id": null,
      "population": 31121,
      "latitude": "49.30880000",
      "longitude": "14.14750000",
      "timezone": "Europe/Prague",
      "wikiDataId": "Q158245",
      "country_code": "CZ",
      "state_code": "31",
      "state_id": 4639,
      "country_id": 58
    },
    {
      "id": 22936,
      "name": "Planá nad Lužnicí",
      "name_default": "Planá nad Lužnicí",
      "native": "Planá nad Lužnicí",
      "type": "city",
      "level": null,
      "parent_id": null,
      "population": 3128,
      "latitude": "49.35444000",
      "longitude": "14.70147000",
      "timezone": "Europe/Prague",
      "wikiDataId": "Q590362",
      "country_code": "CZ",
      "state_code": "31",
      "state_id": 4639,
      "country_id": 58
    },
    {
      "id": 22968,
      "name": "Praktijk",
      "name_default": "Prachatice",
      "native": "Prachatice",
      "type": "city",
      "level": null,
      "parent_id": null,
      "population": 11119,
      "latitude": "49.01292000",
      "longitude": "13.99752000",
      "timezone": "Europe/Prague",
      "wikiDataId": "Q327764",
      "country_code": "CZ",
      "state_code": "31",
      "state_id": 4639,
      "country_id": 58
    },
    {
      "id": 22982,
      "name": "Protivín",
      "name_default": "Protivín",
      "native": "Protivín",
      "type": "city",
      "level": null,
      "parent_id": null,
      "population": 4764,
      "latitude": "49.19949000",
      "longitude": "14.21717000",
      "timezone": "Europe/Prague",
      "wikiDataId": "Q1017045",
      "country_code": "CZ",
      "state_code": "31",
      "state_id": 4639,
      "country_id": 58
    },
    {
      "id": 23013,
      "name": "Radomyšl",
      "name_default": "Radomyšl",
      "native": "Radomyšl",
      "type": "city",
      "level": null,
      "parent_id": null,
      "population": 1366,
      "latitude": "49.31634000",
      "longitude": "13.93024000",
      "timezone": "Europe/Prague",
      "wikiDataId": "Q1088799",
      "country_code": "CZ",
      "state_code": "31",
      "state_id": 4639,
      "country_id": 58
    },
    {
      "id": 23049,
      "name": "Rudolfov",
      "name_default": "Rudolfov",
      "native": "Rudolf",
      "type": "city",
      "level": null,
      "parent_id": null,
      "population": 2587,
      "latitude": "48.99339000",
      "longitude": "14.54179000",
      "timezone": "Europe/Prague",
      "wikiDataId": "Q1713787",
      "country_code": "CZ",
      "state_code": "31",
      "state_id": 4639,
      "country_id": 58
    },
    {
      "id": 23063,
      "name": "Sedlice",
      "name_default": "Sedlice",
      "native": "Sedlo",
      "type": "city",
      "level": null,
      "parent_id": null,
      "population": 1276,
      "latitude": "48.77401000",
      "longitude": "14.39115000",
      "timezone": "Europe/Prague",
      "wikiDataId": "Q12051250",
      "country_code": "CZ",
      "state_code": "31",
      "state_id": 4639,
      "country_id": 58
    },
    {
      "id": 23069,
      "name": "Sepekov",
      "name_default": "Sepekov",
      "native": "Sepekov",
      "type": "city",
      "level": null,
      "parent_id": null,
      "population": 1356,
      "latitude": "49.42865000",
      "longitude": "14.41815000",
      "timezone": "Europe/Prague",
      "wikiDataId": "Q582652",
      "country_code": "CZ",
      "state_code": "31",
      "state_id": 4639,
      "country_id": 58
    },
    {
      "id": 23414,
      "name": "Ševětín",
      "name_default": "Ševětín",
      "native": "Ševětín",
      "type": "city",
      "level": null,
      "parent_id": null,
      "population": 1367,
      "latitude": "49.10005000",
      "longitude": "14.57220000",
      "timezone": "Europe/Prague",
      "wikiDataId": "Q391492",
      "country_code": "CZ",
      "state_code": "31",
      "state_id": 4639,
      "country_id": 58
    },
    {
      "id": 23071,
      "name": "Sezimovo Ústí",
      "name_default": "Sezimovo Ústí",
      "native": "Sezimovo Ústí",
      "type": "city",
      "level": null,
      "parent_id": null,
      "population": 7097,
      "latitude": "49.38519000",
      "longitude": "14.68480000",
      "timezone": "Europe/Prague",
      "wikiDataId": "Q958157",
      "country_code": "CZ",
      "state_code": "31",
      "state_id": 4639,
      "country_id": 58
    },
    {
      "id": 23083,
      "name": "Slavonice",
      "name_default": "Slavonice",
      "native": "Slavonice",
      "type": "city",
      "level": null,
      "parent_id": null,
      "population": 2229,
      "latitude": "48.99753000",
      "longitude": "15.35154000",
      "timezone": "Europe/Prague",
      "wikiDataId": "Q1727398",
      "country_code": "CZ",
      "state_code": "31",
      "state_id": 4639,
      "country_id": 58
    },
    {
      "id": 23092,
      "name": "Soběslav",
      "name_default": "Soběslav",
      "native": "Soběslav",
      "type": "city",
      "level": null,
      "parent_id": null,
      "population": 7070,
      "latitude": "49.25993000",
      "longitude": "14.71861000",
      "timezone": "Europe/Prague",
      "wikiDataId": "Q615138",
      "country_code": "CZ",
      "state_code": "31",
      "state_id": 4639,
      "country_id": 58
    },
    {
      "id": 23098,
      "name": "Srubec",
      "name_default": "Srubec",
      "native": "Srubec",
      "type": "city",
      "level": null,
      "parent_id": null,
      "population": 1107,
      "latitude": "48.94806000",
      "longitude": "14.54131000",
      "timezone": "Europe/Prague",
      "wikiDataId": "Q546935",
      "country_code": "CZ",
      "state_code": "31",
      "state_id": 4639,
      "country_id": 58
    },
    {
      "id": 23099,
      "name": "Saai",
      "name_default": "Stachy",
      "native": "Stachy",
      "type": "city",
      "level": null,
      "parent_id": null,
      "population": 1222,
      "latitude": "49.10179000",
      "longitude": "13.66659000",
      "timezone": "Europe/Prague",
      "wikiDataId": "Q132422",
      "country_code": "CZ",
      "state_code": "31",
      "state_id": 4639,
      "country_id": 58
    },
    {
      "id": 23120,
      "name": "Strakonice",
      "name_default": "Strakonice",
      "native": "Strakonice",
      "type": "city",
      "level": null,
      "parent_id": null,
      "population": 22355,
      "latitude": "49.26141000",
      "longitude": "13.90237000",
      "timezone": "Europe/Prague",
      "wikiDataId": "Q750224",
      "country_code": "CZ",
      "state_code": "31",
      "state_id": 4639,
      "country_id": 58
    },
    {
      "id": 23123,
      "name": "Strmilov",
      "name_default": "Strmilov",
      "native": "Porážka",
      "type": "city",
      "level": null,
      "parent_id": null,
      "population": 1403,
      "latitude": "49.15846000",
      "longitude": "15.19934000",
      "timezone": "Europe/Prague",
      "wikiDataId": "Q937688",
      "country_code": "CZ",
      "state_code": "31",
      "state_id": 4639,
      "country_id": 58
    },
    {
      "id": 23124,
      "name": "Strunkovice nad Blanicí",
      "name_default": "Strunkovice nad Blanicí",
      "native": "Strunkovice nad Blanicí",
      "type": "city",
      "level": null,
      "parent_id": null,
      "population": 1317,
      "latitude": "49.08402000",
      "longitude": "14.05522000",
      "timezone": "Europe/Prague",
      "wikiDataId": "Q288709",
      "country_code": "CZ",
      "state_code": "31",
      "state_id": 4639,
      "country_id": 58
    },
    {
      "id": 23133,
      "name": "Studená",
      "name_default": "Studená",
      "native": "Studená",
      "type": "city",
      "level": null,
      "parent_id": null,
      "population": 2464,
      "latitude": "49.18516000",
      "longitude": "15.28688000",
      "timezone": "Europe/Prague",
      "wikiDataId": "Q1818151",
      "country_code": "CZ",
      "state_code": "31",
      "state_id": 4639,
      "country_id": 58
    },
    {
      "id": 23141,
      "name": "Suchdol nad Lužnicí",
      "name_default": "Suchdol nad Lužnicí",
      "native": "Suchdol nad Lužnicí",
      "type": "city",
      "level": null,
      "parent_id": null,
      "population": 3597,
      "latitude": "48.89000000",
      "longitude": "14.87720000",
      "timezone": "Europe/Prague",
      "wikiDataId": "Q2305015",
      "country_code": "CZ",
      "state_code": "31",
      "state_id": 4639,
      "country_id": 58
    },
    {
      "id": 23189,
      "name": "Tábor",
      "name_default": "Tábor",
      "native": "Tábor",
      "type": "city",
      "level": null,
      "parent_id": null,
      "population": 34356,
      "latitude": "49.41441000",
      "longitude": "14.65780000",
      "timezone": "Europe/Prague",
      "wikiDataId": "Q193721",
      "country_code": "CZ",
      "state_code": "31",
      "state_id": 4639,
      "country_id": 58
    },
    {
      "id": 23200,
      "name": "Třeboň",
      "name_default": "Třeboň",
      "native": "Třeboň",
      "type": "city",
      "level": null,
      "parent_id": null,
      "population": 8270,
      "latitude": "49.00364000",
      "longitude": "14.77065000",
      "timezone": "Europe/Prague",
      "wikiDataId": "Q773312",
      "country_code": "CZ",
      "state_code": "31",
      "state_id": 4639,
      "country_id": 58
    },
    {
      "id": 23173,
      "name": "Trhové Sviny",
      "name_default": "Trhové Sviny",
      "native": "Trhové Sviny",
      "type": "city",
      "level": null,
      "parent_id": null,
      "population": 5262,
      "latitude": "48.84231000",
      "longitude": "14.63924000",
      "timezone": "Europe/Prague",
      "wikiDataId": "Q1019315",
      "country_code": "CZ",
      "state_code": "31",
      "state_id": 4639,
      "country_id": 58
    },
    {
      "id": 23190,
      "name": "Týn nad Vltavou",
      "name_default": "Týn nad Vltavou",
      "native": "Týn nad Vltavou",
      "type": "city",
      "level": null,
      "parent_id": null,
      "population": 7774,
      "latitude": "49.22340000",
      "longitude": "14.42057000",
      "timezone": "Europe/Prague",
      "wikiDataId": "Q815541",
      "country_code": "CZ",
      "state_code": "31",
      "state_id": 4639,
      "country_id": 58
    },
    {
      "id": 23214,
      "name": "Vacov",
      "name_default": "Vacov",
      "native": "Vacv",
      "type": "city",
      "level": null,
      "parent_id": null,
      "population": 1372,
      "latitude": "49.13686000",
      "longitude": "13.72911000",
      "timezone": "Europe/Prague",
      "wikiDataId": "Q1933009",
      "country_code": "CZ",
      "state_code": "31",
      "state_id": 4639,
      "country_id": 58
    },
    {
      "id": 23313,
      "name": "Včelná",
      "name_default": "Včelná",
      "native": "Včelná",
      "type": "city",
      "level": null,
      "parent_id": null,
      "population": 1504,
      "latitude": "48.92373000",
      "longitude": "14.45383000",
      "timezone": "Europe/Prague",
      "wikiDataId": "Q2296231",
      "country_code": "CZ",
      "state_code": "31",
      "state_id": 4639,
      "country_id": 58
    },
    {
      "id": 23228,
      "name": "Velešín",
      "name_default": "Velešín",
      "native": "Velešín",
      "type": "city",
      "level": null,
      "parent_id": null,
      "population": 3861,
      "latitude": "48.82949000",
      "longitude": "14.46252000",
      "timezone": "Europe/Prague",
      "wikiDataId": "Q2092152",
      "country_code": "CZ",
      "state_code": "31",
      "state_id": 4639,
      "country_id": 58
    },
    {
      "id": 23261,
      "name": "Veselí nad Lužnicí",
      "name_default": "Veselí nad Lužnicí",
      "native": "Veselí nad Lužnicí",
      "type": "city",
      "level": null,
      "parent_id": null,
      "population": 6515,
      "latitude": "49.18430000",
      "longitude": "14.69734000",
      "timezone": "Europe/Prague",
      "wikiDataId": "Q612646",
      "country_code": "CZ",
      "state_code": "31",
      "state_id": 4639,
      "country_id": 58
    },
    {
      "id": 23315,
      "name": "Větřní",
      "name_default": "Větřní",
      "native": "Větřní",
      "type": "city",
      "level": null,
      "parent_id": null,
      "population": 3761,
      "latitude": "48.77425000",
      "longitude": "14.28616000",
      "timezone": "Europe/Prague",
      "wikiDataId": "Q2302958",
      "country_code": "CZ",
      "state_code": "31",
      "state_id": 4639,
      "country_id": 58
    },
    {
      "id": 23271,
      "name": "Vimperk",
      "name_default": "Vimperk",
      "native": "Vimperk",
      "type": "city",
      "level": null,
      "parent_id": null,
      "population": 7289,
      "latitude": "49.05857000",
      "longitude": "13.78286000",
      "timezone": "Europe/Prague",
      "wikiDataId": "Q1013919",
      "country_code": "CZ",
      "state_code": "31",
      "state_id": 4639,
      "country_id": 58
    },
    {
      "id": 23279,
      "name": "Vlachovo Březí",
      "name_default": "Vlachovo Březí",
      "native": "Vlachovo Březí",
      "type": "city",
      "level": null,
      "parent_id": null,
      "population": 1750,
      "latitude": "49.08135000",
      "longitude": "13.95842000",
      "timezone": "Europe/Prague",
      "wikiDataId": "Q1401340",
      "country_code": "CZ",
      "state_code": "31",
      "state_id": 4639,
      "country_id": 58
    },
    {
      "id": 23286,
      "name": "Vodňany",
      "name_default": "Vodňany",
      "native": "Vodňany",
      "type": "city",
      "level": null,
      "parent_id": null,
      "population": 7383,
      "latitude": "49.14789000",
      "longitude": "14.17513000",
      "timezone": "Europe/Prague",
      "wikiDataId": "Q1008983",
      "country_code": "CZ",
      "state_code": "31",
      "state_id": 4639,
      "country_id": 58
    },
    {
      "id": 23288,
      "name": "Volary",
      "name_default": "Volary",
      "native": "Volary",
      "type": "city",
      "level": null,
      "parent_id": null,
      "population": 3692,
      "latitude": "48.90881000",
      "longitude": "13.88657000",
      "timezone": "Europe/Prague",
      "wikiDataId": "Q509207",
      "country_code": "CZ",
      "state_code": "31",
      "state_id": 4639,
      "country_id": 58
    },
    {
      "id": 23289,
      "name": "Volyně",
      "name_default": "Volyně",
      "native": "Volyně",
      "type": "city",
      "level": null,
      "parent_id": null,
      "population": 3036,
      "latitude": "49.16578000",
      "longitude": "13.88624000",
      "timezone": "Europe/Prague",
      "wikiDataId": "Q1017889",
      "country_code": "CZ",
      "state_code": "31",
      "state_id": 4639,
      "country_id": 58
    },
    {
      "id": 23309,
      "name": "Vyšší Brod",
      "name_default": "Vyšší Brod",
      "native": "Vyšší Brod",
      "type": "city",
      "level": null,
      "parent_id": null,
      "population": 2597,
      "latitude": "48.61598000",
      "longitude": "14.31183000",
      "timezone": "Europe/Prague",
      "wikiDataId": "Q1019688",
      "country_code": "CZ",
      "state_code": "31",
      "state_id": 4639,
      "country_id": 58
    },
    {
      "id": 23337,
      "name": "Zdíkov",
      "name_default": "Zdíkov",
      "native": "Předpovídačů",
      "type": "city",
      "level": null,
      "parent_id": null,
      "population": 1616,
      "latitude": "49.08456000",
      "longitude": "13.69738000",
      "timezone": "Europe/Prague",
      "wikiDataId": "Q169283",
      "country_code": "CZ",
      "state_code": "31",
      "state_id": 4639,
      "country_id": 58
    },
    {
      "id": 23341,
      "name": "Zliv",
      "name_default": "Zliv",
      "native": "Zliv",
      "type": "city",
      "level": null,
      "parent_id": null,
      "population": 3453,
      "latitude": "49.06608000",
      "longitude": "14.36613000",
      "timezone": "Europe/Prague",
      "wikiDataId": "Q207251",
      "country_code": "CZ",
      "state_code": "31",
      "state_id": 4639,
      "country_id": 58
    }
  ]
}
