{
  "locale": "zh-CN",
  "country": {
    "id": 90,
    "code": "GT",
    "iso3": "GTM",
    "numeric_code": "320",
    "name": "危地马拉",
    "name_default": "Guatemala",
    "native": "Guatemala",
    "capital": "Guatemala City",
    "phonecode": "502",
    "currency": "GTQ",
    "currency_name": "Guatemalan quetzal",
    "currency_symbol": "Q",
    "tld": ".gt",
    "population": 18079810,
    "gdp": 121177,
    "region": "Americas",
    "region_id": 2,
    "subregion": "Central America",
    "subregion_id": 9,
    "nationality": "Guatemalan",
    "timezones": [
      {
        "zoneName": "America/Guatemala",
        "gmtOffset": -21600,
        "gmtOffsetName": "UTC-06:00",
        "abbreviation": "CST",
        "tzName": "Central Standard Time (North America"
      }
    ],
    "latitude": "15.50000000",
    "longitude": "-90.25000000",
    "emoji": "🇬🇹",
    "emojiU": "U+1F1EC U+1F1F9"
  },
  "state": {
    "id": 3665,
    "code": "06",
    "iso2": "06",
    "iso3166_2": "GT-06",
    "fips_code": "06",
    "name": "圣罗莎",
    "name_default": "Santa Rosa ",
    "native": "Santa Rosa",
    "type": "department",
    "level": null,
    "parent_id": null,
    "population": null,
    "latitude": "14.15015230",
    "longitude": "-90.35088180",
    "timezone": "America/Guatemala",
    "wikiDataId": "Q885656",
    "country_code": "GT"
  },
  "cities": [
    {
      "id": 53434,
      "name": "巴贝雷纳",
      "name_default": "Barberena",
      "native": "Barbería",
      "type": "adm2",
      "level": null,
      "parent_id": null,
      "population": 47093,
      "latitude": "14.30739000",
      "longitude": "-90.36156000",
      "timezone": "America/Guatemala",
      "wikiDataId": "Q2718316",
      "country_code": "GT",
      "state_code": "06",
      "state_id": 3665,
      "country_id": 90
    },
    {
      "id": 53442,
      "name": "卡西利亚斯",
      "name_default": "Casillas",
      "native": "Casillas",
      "type": "adm2",
      "level": null,
      "parent_id": null,
      "population": 7698,
      "latitude": "14.42222000",
      "longitude": "-90.24417000",
      "timezone": "America/Guatemala",
      "wikiDataId": "Q1748683",
      "country_code": "GT",
      "state_code": "06",
      "state_id": 3665,
      "country_id": 90
    },
    {
      "id": 53456,
      "name": "奇基穆利拉",
      "name_default": "Chiquimulilla",
      "native": "Chiquimulilla",
      "type": "city",
      "level": null,
      "parent_id": null,
      "population": 12842,
      "latitude": "14.08380000",
      "longitude": "-90.38547000",
      "timezone": "America/Guatemala",
      "wikiDataId": "Q202128",
      "country_code": "GT",
      "state_code": "06",
      "state_id": 3665,
      "country_id": 90
    },
    {
      "id": 53475,
      "name": "库伊拉帕",
      "name_default": "Cuilapa",
      "native": "Cuilapa",
      "type": "adm1",
      "level": null,
      "parent_id": null,
      "population": 46974,
      "latitude": "14.27639000",
      "longitude": "-90.29889000",
      "timezone": "America/Guatemala",
      "wikiDataId": "Q1015941",
      "country_code": "GT",
      "state_code": "06",
      "state_id": 3665,
      "country_id": 90
    },
    {
      "id": 53501,
      "name": "瓜萨卡潘",
      "name_default": "Guazacapán",
      "native": "Guazacapán",
      "type": "adm2",
      "level": null,
      "parent_id": null,
      "population": 22197,
      "latitude": "14.07417000",
      "longitude": "-90.41667000",
      "timezone": "America/Guatemala",
      "wikiDataId": "Q2401701",
      "country_code": "GT",
      "state_code": "06",
      "state_id": 3665,
      "country_id": 90
    },
    {
      "id": 53547,
      "name": "卡西利亚斯市政府",
      "name_default": "Municipio de Casillas",
      "native": "Municipio de Casillas",
      "type": "adm2",
      "level": null,
      "parent_id": null,
      "population": null,
      "latitude": "14.37854000",
      "longitude": "-90.17260000",
      "timezone": "America/Guatemala",
      "wikiDataId": "Q2403612",
      "country_code": "GT",
      "state_code": "06",
      "state_id": 3665,
      "country_id": 90
    },
    {
      "id": 53553,
      "name": "奇基穆利利亚市",
      "name_default": "Municipio de Chiquimulilla",
      "native": "Municipio de Chiquimulilla",
      "type": "city",
      "level": null,
      "parent_id": null,
      "population": null,
      "latitude": "14.09716000",
      "longitude": "-90.37903000",
      "timezone": "America/Guatemala",
      "wikiDataId": "Q2403612",
      "country_code": "GT",
      "state_code": "06",
      "state_id": 3665,
      "country_id": 90
    },
    {
      "id": 53562,
      "name": "瓜萨卡潘市",
      "name_default": "Municipio de Guazacapán",
      "native": "Municipio de Guazacapán",
      "type": "adm2",
      "level": null,
      "parent_id": null,
      "population": null,
      "latitude": "14.01786000",
      "longitude": "-90.43400000",
      "timezone": "America/Guatemala",
      "wikiDataId": "Q2403612",
      "country_code": "GT",
      "state_code": "06",
      "state_id": 3665,
      "country_id": 90
    },
    {
      "id": 53606,
      "name": "新圣罗莎",
      "name_default": "Nueva Santa Rosa",
      "native": "Nueva Santa Rosa",
      "type": "adm2",
      "level": null,
      "parent_id": null,
      "population": 10130,
      "latitude": "14.38111000",
      "longitude": "-90.27611000",
      "timezone": "America/Guatemala",
      "wikiDataId": "Q2402348",
      "country_code": "GT",
      "state_code": "06",
      "state_id": 3665,
      "country_id": 90
    },
    {
      "id": 53612,
      "name": "清唱剧",
      "name_default": "Oratorio",
      "native": "Oratorio",
      "type": "adm2",
      "level": null,
      "parent_id": null,
      "population": 10155,
      "latitude": "14.22806000",
      "longitude": "-90.17583000",
      "timezone": "America/Guatemala",
      "wikiDataId": "Q3884406",
      "country_code": "GT",
      "state_code": "06",
      "state_id": 3665,
      "country_id": 90
    },
    {
      "id": 53633,
      "name": "新维尼亚斯镇",
      "name_default": "Pueblo Nuevo Viñas",
      "native": "Pueblo Nuevo Viñas",
      "type": "adm2",
      "level": null,
      "parent_id": null,
      "population": 4211,
      "latitude": "14.22576000",
      "longitude": "-90.47613000",
      "timezone": "America/Guatemala",
      "wikiDataId": "Q2402134",
      "country_code": "GT",
      "state_code": "06",
      "state_id": 3665,
      "country_id": 90
    },
    {
      "id": 53699,
      "name": "圣胡安特夸科",
      "name_default": "San Juan Tecuaco",
      "native": "San Juan Tecuaco",
      "type": "adm2",
      "level": null,
      "parent_id": null,
      "population": 2210,
      "latitude": "14.08361000",
      "longitude": "-90.26649000",
      "timezone": "America/Guatemala",
      "wikiDataId": "Q2372941",
      "country_code": "GT",
      "state_code": "06",
      "state_id": 3665,
      "country_id": 90
    },
    {
      "id": 53733,
      "name": "圣拉斐尔拉斯弗洛雷斯",
      "name_default": "San Rafael Las Flores",
      "native": "San Rafael Las Flores",
      "type": "adm2",
      "level": null,
      "parent_id": null,
      "population": 2572,
      "latitude": "14.48139000",
      "longitude": "-90.17333000",
      "timezone": "America/Guatemala",
      "wikiDataId": "Q1748669",
      "country_code": "GT",
      "state_code": "06",
      "state_id": 3665,
      "country_id": 90
    },
    {
      "id": 53757,
      "name": "圣克鲁斯·纳兰霍",
      "name_default": "Santa Cruz Naranjo",
      "native": "Santa Cruz Naranjo",
      "type": "adm2",
      "level": null,
      "parent_id": null,
      "population": 6254,
      "latitude": "14.38806000",
      "longitude": "-90.36972000",
      "timezone": "America/Guatemala",
      "wikiDataId": "Q979193",
      "country_code": "GT",
      "state_code": "06",
      "state_id": 3665,
      "country_id": 90
    },
    {
      "id": 53766,
      "name": "圣玛丽亚伊斯瓦坦",
      "name_default": "Santa María Ixhuatán",
      "native": "Santa María Ixhuatán",
      "type": "adm2",
      "level": null,
      "parent_id": null,
      "population": 3634,
      "latitude": "14.19000000",
      "longitude": "-90.27472000",
      "timezone": "America/Guatemala",
      "wikiDataId": "Q1748654",
      "country_code": "GT",
      "state_code": "06",
      "state_id": 3665,
      "country_id": 90
    },
    {
      "id": 53769,
      "name": "圣罗莎·德利马",
      "name_default": "Santa Rosa de Lima",
      "native": "Santa Rosa de Lima",
      "type": "adm2",
      "level": null,
      "parent_id": null,
      "population": 5984,
      "latitude": "14.38806000",
      "longitude": "-90.29556000",
      "timezone": "America/Guatemala",
      "wikiDataId": "Q3949243",
      "country_code": "GT",
      "state_code": "06",
      "state_id": 3665,
      "country_id": 90
    },
    {
      "id": 53789,
      "name": "塔西斯科",
      "name_default": "Taxisco",
      "native": "Taxisco",
      "type": "city",
      "level": null,
      "parent_id": null,
      "population": 6518,
      "latitude": "14.06719000",
      "longitude": "-90.46791000",
      "timezone": "America/Guatemala",
      "wikiDataId": "Q2402116",
      "country_code": "GT",
      "state_code": "06",
      "state_id": 3665,
      "country_id": 90
    }
  ]
}
